<PropertyList>

<model>
	<path>Aircraft/747-400/Models/Cockpit/display-text.xml</path>
	<offsets>
		<x-m> 0.004</x-m>
		<y-m> 0.000</y-m>
		<z-m> 0.110</z-m>
	</offsets>
	<overlay>
		<params>
			<text type="string">PERF INIT</text>
			<character-size type="double">0.007</character-size>
			<color>
				<red   type="double">0.1</red>
				<green type="double">1.0</green>
				<blue  type="double">0.1</blue>
			</color>
		</params>
	</overlay>
</model>

<model>
	<path>Aircraft/747-400/Models/Cockpit/display-number.xml</path>
	<offsets>
		<x-m> 0.004</x-m>
		<y-m>-0.041</y-m>
		<z-m> 0.098</z-m>
	</offsets>
	<overlay>
		<params>
			<property type="string">/fdm/jsbsim/inertia/weight-lbs</property>
			<format type="string">%03.1f</format>
			<factor>0.001</factor>
			<character-size type="double">0.007</character-size>
			<color>
				<red   type="double">0.1</red>
				<green type="double">1.0</green>
				<blue  type="double">0.1</blue>
			</color>
		</params>
	</overlay>
</model>

<model>
	<path>Aircraft/747-400/Models/Cockpit/display-number.xml</path>
	<offsets>
		<x-m> 0.004</x-m>
		<y-m>-0.041</y-m>
		<z-m> 0.085</z-m>
	</offsets>
	<overlay>
		<params>
			<property type="string">/fdm/jsbsim/propulsion/total-fuel-lbs</property>
			<format type="string">%03.1f</format>
			<factor>0.001</factor>
			<character-size type="double">0.007</character-size>
			<color>
				<red   type="double">0.1</red>
				<green type="double">1.0</green>
				<blue  type="double">0.1</blue>
			</color>
		</params>
	</overlay>
</model>

<model>
	<path>Aircraft/747-400/Models/Cockpit/display-number.xml</path>
	<offsets>
		<x-m> 0.004</x-m>
		<y-m>-0.041</y-m>
		<z-m> 0.072</z-m>
	</offsets>
	<overlay>
		<params>
			<property type="string">/fdm/jsbsim/inertia/empty-weight-lbs</property>
			<format type="string">%03.1f</format>
			<factor>0.001</factor>
			<character-size type="double">0.007</character-size>
			<color>
				<red   type="double">0.1</red>
				<green type="double">1.0</green>
				<blue  type="double">0.1</blue>
			</color>
		</params>
	</overlay>
</model>

<model>
	<path>Aircraft/747-400/Models/Cockpit/display-text.xml</path>
	<offsets>
		<x-m> 0.004</x-m>
		<y-m> 0.000</y-m>
		<z-m> 0.040</z-m>
	</offsets>
	<overlay>
		<params>
			<text type="string">------------------------</text>
			<character-size type="double">0.012</character-size>
			<color>
				<red   type="double">0.1</red>
				<green type="double">1.0</green>
				<blue  type="double">0.1</blue>
			</color>
		</params>
	</overlay>
</model>

<model>
	<path>Aircraft/747-400/Models/Cockpit/display-text.xml</path>
	<offsets>
		<x-m> 0.004</x-m>
		<y-m>-0.040</y-m>
		<z-m> 0.034</z-m>
	</offsets>
	<overlay>
		<params>
			<text type="string">&lt;INDEX</text>
			<character-size type="double">0.007</character-size>
			<color>
				<red   type="double">0.1</red>
				<green type="double">1.0</green>
				<blue  type="double">0.1</blue>
			</color>
		</params>
	</overlay>
</model>

<model>
	<path>Aircraft/747-400/Models/Cockpit/display-text.xml</path>
	<offsets>
		<x-m> 0.004</x-m>
		<y-m> 0.032</y-m>
		<z-m> 0.034</z-m>
	</offsets>
	<overlay>
		<params>
			<text type="string">THRUST LIM&gt;</text>
			<character-size type="double">0.007</character-size>
			<color>
				<red   type="double">0.1</red>
				<green type="double">1.0</green>
				<blue  type="double">0.1</blue>
			</color>
		</params>
	</overlay>
</model>

</PropertyList>