<PropertyList>

<path>pedestal.ac</path>

<!-- THROTTLE LEVER -->
<!-- ENGINE 1 -->
<animation>
<type>rotate</type>
<object-name>throttle_eng.1</object-name>
<object-name>reverser.1</object-name>
<property>/controls/engines/engine/throttle</property>
<interpolation>
 <entry>
     <ind>0</ind>
     <dep>15</dep>
    </entry>
 <entry>
     <ind>1</ind>
     <dep>-20</dep>
    </entry>
</interpolation>
<center>
<x-m>1.143</x-m>
<y-m>0</y-m>
<z-m>0.362</z-m>
</center>
<axis>
<x>0.0</x>
<y>1.0</y>
<z>0</z>
</axis>
</animation>

<animation>
<type>rotate</type>
<object-name>reverser.1</object-name>
<property>/controls/engines/engine/reverser</property>
<interpolation>
<entry>
     <ind>0</ind>
     <dep>0</dep>
    </entry>
<entry>
     <ind>1</ind>
     <dep>25</dep>
    </entry>
</interpolation>
<center>
<x-m>1.12</x-m>
<y-m>0</y-m>
<z-m>0.54</z-m>
</center>
<axis>
<x>0.0</x>
<y>1.0</y>
<z>0</z>
</axis>
</animation>

<!-- ENGINE 2 -->
<animation>
<type>rotate</type>
<object-name>throttle_eng.2</object-name>
<object-name>reverser.2</object-name>
<property>/controls/engines/engine[1]/throttle</property>
  
<interpolation>
    
<entry>
     <ind>0</ind>
     <dep>15</dep>
    </entry>
        
<entry>
     <ind>1</ind>
     <dep>-20</dep>
    </entry>
 
</interpolation>
<center>
<x-m>1.143</x-m>
<y-m>0</y-m>
<z-m>0.362</z-m>
</center>
<axis>
<x>0.0</x>
<y>1.0</y>
<z>0</z>
</axis>
</animation>

<animation>
<type>rotate</type>
<object-name>reverser.2</object-name>
<property>/controls/engines/engine[1]/reverser</property>
<interpolation>
<entry>
     <ind>0</ind>
     <dep>0</dep>
    </entry>
<entry>
     <ind>1</ind>
     <dep>25</dep>
    </entry>
</interpolation>
<center>
<x-m>1.12</x-m>
<y-m>0</y-m>
<z-m>0.54</z-m>
</center>
<axis>
<x>0.0</x>
<y>1.0</y>
<z>0</z>
</axis>
</animation>

<!-- ENGINE 3 -->
<animation>
<type>rotate</type>
<object-name>throttle_eng.3</object-name>
<object-name>reverser.3</object-name>
<property>/controls/engines/engine[2]/throttle</property>
<interpolation>
<entry>
     <ind>0</ind>
     <dep>15</dep>
    </entry>
<entry>
     <ind>1</ind>
     <dep>-20</dep>
    </entry>
</interpolation>
<center>
<x-m>1.143</x-m>
<y-m>0</y-m>
<z-m>0.362</z-m>
</center>
<axis>
<x>0.0</x>
<y>1.0</y>
<z>0</z>
</axis>
</animation>

<animation>
<type>rotate</type>  
<object-name>reverser.3</object-name>
<property>/controls/engines/engine[2]/reverser</property>
<interpolation>
<entry>
     <ind>0</ind>
     <dep>0</dep>
    </entry>
<entry>
     <ind>1</ind>
     <dep>25</dep>
    </entry>
</interpolation>
<center>
<x-m>1.12</x-m>
<y-m>0</y-m>
<z-m>0.54</z-m>
</center>
<axis>
<x>0.0</x>
<y>1.0</y>
<z>0</z>
</axis>
</animation>

<!-- ENGINE 4 -->
<animation>
<type>rotate</type>
<object-name>throttle_eng.4</object-name>
<object-name>reverser.4</object-name>
<property>/controls/engines/engine[3]/throttle</property>
<interpolation>
<entry>
     <ind>0</ind>
     <dep>15</dep>
    </entry>
<entry>
     <ind>1</ind>
     <dep>-20</dep>
    </entry>
</interpolation>  
<center>
<x-m>1.143</x-m>
<y-m>0</y-m>
<z-m>0.362</z-m>
</center>
<axis>
<x>0.0</x>
<y>1.0</y>
<z>0</z>
</axis>
</animation>

<animation>
<type>rotate</type>
<object-name>reverser.4</object-name>
<property>/controls/engines/engine[3]/reverser</property>
<interpolation>
<entry>
     <ind>0</ind>
     <dep>0</dep>
    </entry>
<entry>
     <ind>1</ind>
     <dep>25</dep>
    </entry>
</interpolation>
<center>
<x-m>1.12</x-m>
<y-m>0</y-m>
<z-m>0.54</z-m>
</center>
<axis>
<x>0.0</x>
<y>1.0</y>
<z>0</z>
</axis>
</animation>

<!-- FLAPS LEVER -->

<animation>
<type>rotate</type>
<object-name>flap_handle</object-name>
<property>/controls/flight/flaps</property>
<interpolation>
<entry>
     <ind>0</ind>
     <dep>0</dep>
    </entry>
<entry>
     <ind>0.001</ind>
     <dep>9.7</dep>
    </entry>
<entry>
     <ind>0.167</ind>
     <dep>19.4</dep>
    </entry>
<entry>
     <ind>0.333</ind>
     <dep>29.1</dep>
    </entry>
<entry>
     <ind>0.667</ind>
     <dep>38.8</dep>
    </entry>
<entry>
     <ind>0.833</ind>
     <dep>48.5</dep>
    </entry>
<entry>
     <ind>1</ind>
     <dep>58.2</dep>
    </entry>
</interpolation>
<center>
<x-m>1.143</x-m>
<y-m>0</y-m>
<z-m>0.362</z-m>
</center>
<axis>
<x>0.0</x>
<y>1.0</y>
<z>0</z>
</axis>
</animation>

<!-- SPEEDBRAKE LEVER -->

 <animation>
  <type>pick</type>
  <object-name>speedbrake</object-name>
  <action>
   <button>0</button>
   <repeatable>false</repeatable>  
   <binding>
    <command>property-toggle</command>
    <property>/controls/flight/speedbrake</property>
   </binding>
  </action>
 </animation>

<animation>
<type>rotate</type>
<object-name>speedbrake</object-name>
<property>/controls/flight/speedbrake</property>
<factor>58.2</factor>
<center>
<x-m>1.143</x-m>
<y-m>0</y-m>
<z-m>0.362</z-m>
</center>
<axis>
<x>0</x>
<y>1</y>
<z>0</z>
</axis>
</animation>

<!-- FUEL CONTROL -->

 <animation>
  <type>pick</type>
  <object-name>fuel_ctrl.1</object-name>
  <action>
   <button>0</button>
   <repeatable>false</repeatable>  
   <binding>
    <command>property-toggle</command>
    <property>/controls/engines/engine/cutoff</property>
   </binding>
  </action>
 </animation>

<animation>
<type>rotate</type>
<object-name>fuel_ctrl.1</object-name>
<property>/controls/engines/engine/cutoff</property>
<factor>25</factor>
<center>
<x-m>1.236</x-m>
<y-m>0</y-m>
<z-m>0.462</z-m>
</center>
<axis>
<x>0</x>
<y>1</y>
<z>0</z>
</axis>
</animation>

 <animation>
  <type>pick</type>
  <object-name>fuel_ctrl.2</object-name>
  <action>
   <button>0</button>
   <repeatable>false</repeatable>  
   <binding>
    <command>property-toggle</command>
    <property>/controls/engines/engine[1]/cutoff</property>
   </binding>
  </action>
 </animation>

<animation>
<type>rotate</type>
<object-name>fuel_ctrl.2</object-name>
<property>/controls/engines/engine[1]/cutoff</property>
<factor>25</factor>
<center>
<x-m>1.236</x-m>
<y-m>0</y-m>
<z-m>0.462</z-m>
</center>
<axis>
<x>0</x>
<y>1</y>
<z>0</z>
</axis>
</animation>

 <animation>
  <type>pick</type>
  <object-name>fuel_ctrl.3</object-name>
  <action>
   <button>0</button>
   <repeatable>false</repeatable>  
   <binding>
    <command>property-toggle</command>
    <property>/controls/engines/engine[2]/cutoff</property>
   </binding>
  </action>
 </animation>

<animation>
<type>rotate</type>
<object-name>fuel_ctrl.3</object-name>
<property>/controls/engines/engine[2]/cutoff</property>
<factor>25</factor>
<center>
<x-m>1.236</x-m>
<y-m>0</y-m>
<z-m>0.462</z-m>
</center>
<axis>
<x>0</x>
<y>1</y>
<z>0</z>
</axis>
</animation>

 <animation>
  <type>pick</type>
  <object-name>fuel_ctrl.4</object-name>
  <action>
   <button>0</button>
   <repeatable>false</repeatable>  
   <binding>
    <command>property-toggle</command>
    <property>/controls/engines/engine[3]/cutoff</property>
   </binding>
  </action>
 </animation>

<animation>
<type>rotate</type>
<object-name>fuel_ctrl.4</object-name>
<property>/controls/engines/engine[3]/cutoff</property>
<factor>25</factor>
<center>
<x-m>1.236</x-m>
<y-m>0</y-m>
<z-m>0.462</z-m>
</center>
<axis>
<x>0</x>
<y>1</y>
<z>0</z>
</axis>
</animation>

<!-- RADIO -->
<!-- ACTIVE -->
  <animation>
    <type>textranslate</type>
    <object-name>freq_active.1</object-name>
 <property>/instrumentation/comm/frequencies/selected-mhz</property>
    <factor>0.001</factor>
    <step>100.0</step>
    <axis>
      <x>0</x>
      <y>1</y>
      <z>0</z>
    </axis>
  </animation>

   <animation>
    <type>textranslate</type>
    <object-name>freq_active.2</object-name>
 <property>/instrumentation/comm/frequencies/selected-mhz</property>
    <factor>0.01</factor>
    <step>10.0</step>
    <axis>
      <x>0</x>
      <y>1</y>
      <z>0</z>
    </axis>
  </animation>

   <animation>
    <type>textranslate</type>
    <object-name>freq_active.3</object-name>
<property>/instrumentation/comm/frequencies/selected-mhz</property>
    <factor>0.1</factor>
    <step>1.0</step>
    <axis>
      <x>0</x>
      <y>1</y>
      <z>0</z>
    </axis>
  </animation>

   <animation>
    <type>textranslate</type>
    <object-name>freq_active.4</object-name>
 <property>/instrumentation/comm/frequencies/selected-mhz</property>
    <factor>1.0</factor>
    <step>0.1</step>
    <axis>
      <x>0</x>
      <y>1</y>
      <z>0</z>
    </axis>
  </animation>

   <animation>
    <type>textranslate</type>
    <object-name>freq_active.5</object-name>
<property>/instrumentation/comm/frequencies/selected-mhz</property>
    <factor>10.0</factor>
    <step>0.01</step>
    <axis>
      <x>0</x>
      <y>1</y>
      <z>0</z>
    </axis>
  </animation>

   <animation>
    <type>textranslate</type>
    <object-name>freq_active.6</object-name>
    <property>/instrumentation/comm/frequencies/selected-mhz</property>
    <factor>100.0</factor>
    <step>0.001</step>
    <axis>
      <x>0</x>
      <y>1</y>
      <z>0</z>
    </axis>
  </animation>

<!-- RADIO -->
<!-- STANDBY -->

  <animation>
    <type>textranslate</type>
    <object-name>freq_stby.1</object-name>
 <property>/instrumentation/comm/frequencies/standby-mhz</property>
    <factor>0.001</factor>
    <step>100.0</step>
    <axis>
      <x>0</x>
      <y>1</y>
      <z>0</z>
    </axis>
  </animation>

   <animation>
    <type>textranslate</type>
    <object-name>freq_stby.2</object-name>
 <property>/instrumentation/comm/frequencies/standby-mhz</property>
    <factor>0.01</factor>
    <step>10.0</step>
    <axis>
      <x>0</x>
      <y>1</y>
      <z>0</z>
    </axis>
  </animation>

   <animation>
    <type>textranslate</type>
    <object-name>freq_stby.3</object-name>
<property>/instrumentation/comm/frequencies/standby-mhz</property>
    <factor>0.1</factor>
    <step>1.0</step>
    <axis>
      <x>0</x>
      <y>1</y>
      <z>0</z>
    </axis>
  </animation>

   <animation>
    <type>textranslate</type>
    <object-name>freq_stby.4</object-name>
 <property>/instrumentation/comm/frequencies/standby-mhz</property>
    <factor>1.0</factor>
    <step>0.1</step>
    <axis>
      <x>0</x>
      <y>1</y>
      <z>0</z>
    </axis>
  </animation>

   <animation>
    <type>textranslate</type>
    <object-name>freq_stby.5</object-name>
<property>/instrumentation/comm/frequencies/standby-mhz</property>
    <factor>10.0</factor>
    <step>0.01</step>
    <axis>
      <x>0</x>
      <y>1</y>
      <z>0</z>
    </axis>
  </animation>

   <animation>
    <type>textranslate</type>
    <object-name>freq_stby.6</object-name>
    <property>/instrumentation/comm/frequencies/standby-mhz</property>
    <factor>100.0</factor>
    <step>0.001</step>
    <axis>
      <x>0</x>
      <y>1</y>
      <z>0</z>
    </axis>
  </animation>

</PropertyList>


