<PropertyList>

<!-- # # # # # # # # # # # # # # # # # # # # # -->
<!-- # Boeing 747-400 EICAS by Gijs de Rooy  # -->
<!-- # # # # # # # # # # # # # # # # # # # # # -->

<path>eicas_gear.ac</path>

<model>
	<path>Aircraft/747-400/Models/Cockpit/Instruments/EICAS/eicas_gear_btms.xml</path>
	<offsets>
		<x-m> 0.007</x-m>
		<y-m>-0.058</y-m>
		<z-m> 0.018</z-m>
	</offsets>
	<overlay>
		<params>
			<btms>/gear/gear[1]/btms</btms>
		</params>
	</overlay>
</model>
<model>
	<path>Aircraft/747-400/Models/Cockpit/Instruments/EICAS/eicas_gear_btms.xml</path>
	<offsets>
		<x-m> 0.007</x-m>
		<y-m>-0.034</y-m>
		<z-m>-0.051</z-m>
	</offsets>
	<overlay>
		<params>
			<btms>/gear/gear[2]/btms</btms>
		</params>
	</overlay>
</model>
<model>
	<path>Aircraft/747-400/Models/Cockpit/Instruments/EICAS/eicas_gear_btms.xml</path>
	<offsets>
		<x-m> 0.007</x-m>
		<y-m> 0.034</y-m>
		<z-m>-0.051</z-m>
	</offsets>
	<overlay>
		<params>
			<btms>/gear/gear[3]/btms</btms>
		</params>
	</overlay>
</model>
<model>
	<path>Aircraft/747-400/Models/Cockpit/Instruments/EICAS/eicas_gear_btms.xml</path>
	<offsets>
		<x-m> 0.007</x-m>
		<y-m> 0.058</y-m>
		<z-m> 0.018</z-m>
	</offsets>
	<overlay>
		<params>
			<btms>/gear/gear[4]/btms</btms>
		</params>
	</overlay>
</model>

<animation>
	<type>select</type>
	<object-name>gear.0.door.open</object-name>
	<condition>
		<greater-than>
			<property>/gear/gear[0]/position-norm</property>
			<value>0</value>
		</greater-than>
	</condition>
</animation>

<animation>
	<type>select</type>
	<object-name>gear.1.door.open</object-name>
	<condition>
		<greater-than>
			<property>/gear/gear[1]/position-norm</property>
			<value>0</value>
		</greater-than>
	</condition>
</animation>

<animation>
	<type>select</type>
	<object-name>gear.2.door.open</object-name>
	<condition>
		<greater-than>
			<property>/gear/gear[2]/position-norm</property>
			<value>0</value>
		</greater-than>
	</condition>
</animation>

<animation>
	<type>select</type>
	<object-name>gear.3.door.open</object-name>
	<condition>
		<greater-than>
			<property>/gear/gear[3]/position-norm</property>
			<value>0</value>
		</greater-than>
	</condition>
</animation>

<animation>
	<type>select</type>
	<object-name>gear.4.door.open</object-name>
	<condition>
		<greater-than>
			<property>/gear/gear[4]/position-norm</property>
			<value>0</value>
		</greater-than>
	</condition>
</animation>

</PropertyList>